channel2index/__init__.py
channel2index/index.py
channel2index-0.0.1.dist-info/LICENSE
channel2index-0.0.1.dist-info/METADATA
channel2index-0.0.1.dist-info/WHEEL
channel2index-0.0.1.dist-info/top_level.txt
channel2index-0.0.1.dist-info/RECORD
