Metadata-Version: 2.1
Name: channel2index
Version: 0.0.1
Summary: Telegram Channel to Index
Home-page: https://github.com/gaoyunzhi/channel2index
Author: Yunzhi Gao
Author-email: gaoyunzhi@gmail.com
License: UNKNOWN
Platform: UNKNOWN
Classifier: Programming Language :: Python :: 3
Classifier: License :: OSI Approved :: MIT License
Classifier: Operating System :: OS Independent
Requires-Python: >=3.0
Requires-Dist: html-telegraph-poster
Requires-Dist: telegram-util (>=0.0.27)
Requires-Dist: pyyaml
Requires-Dist: python-telegram-bot
